crawler/__init__.py
crawler/dev/__init__.py
crawler/dev/_base_client.py
crawler/dev/_client.py
crawler/dev/_compat.py
crawler/dev/_constants.py
crawler/dev/_exceptions.py
crawler/dev/_files.py
crawler/dev/_models.py
crawler/dev/_qs.py
crawler/dev/_resource.py
crawler/dev/_response.py
crawler/dev/_streaming.py
crawler/dev/_types.py
crawler/dev/_version.py
crawler/dev/py.typed
crawler/dev/_utils/__init__.py
crawler/dev/_utils/_compat.py
crawler/dev/_utils/_datetime_parse.py
crawler/dev/_utils/_logs.py
crawler/dev/_utils/_proxy.py
crawler/dev/_utils/_reflection.py
crawler/dev/_utils/_resources_proxy.py
crawler/dev/_utils/_streams.py
crawler/dev/_utils/_sync.py
crawler/dev/_utils/_transform.py
crawler/dev/_utils/_typing.py
crawler/dev/_utils/_utils.py
crawler/dev/lib/.keep
crawler/dev/resources/__init__.py
crawler/dev/resources/files.py
crawler/dev/resources/urls.py
crawler/dev/types/__init__.py
crawler/dev/types/file_extract_text_params.py
crawler/dev/types/file_extract_text_response.py
crawler/dev/types/url_extract_text_params.py
crawler/dev/types/url_extract_text_response.py
crawler_dev-1.3.0.dist-info/METADATA
crawler_dev-1.3.0.dist-info/WHEEL
crawler_dev-1.3.0.dist-info/licenses/LICENSE
crawler_dev-1.3.0.dist-info/RECORD
